[
  {
    "label": "(1) Pooled OLS\nlog spread",
    "n": 246,
    "coef": 0.5309325562594682,
    "se": 0.21718241028852805,
    "p": 0.014499725815903317,
    "r2": 0.37485539999715745,
    "kind": "Pooled OLS",
    "fe": "None"
  },
  {
    "label": "(2) TWFE\nlog spread",
    "n": 246,
    "coef": 0.11794999297870275,
    "se": 0.2110513996729205,
    "p": 0.5768584372717851,
    "r2": 0.09884376015061913,
    "kind": "Panel TWFE",
    "fe": "Country + Year"
  },
  {
    "label": "(3) Pooled OLS\nlog lending",
    "n": 247,
    "coef": 0.231164655113396,
    "se": 0.11949208388786609,
    "p": 0.05304426188231702,
    "r2": 0.3154346835611669,
    "kind": "Pooled OLS",
    "fe": "None"
  },
  {
    "label": "(4) TWFE\nlog lending",
    "n": 247,
    "coef": 0.021545678779062497,
    "se": 0.1508843122748929,
    "p": 0.8865901813239621,
    "r2": 0.06397803923559753,
    "kind": "Panel TWFE",
    "fe": "Country + Year"
  },
  {
    "label": "(5) TWFE\nlog rltir",
    "n": 125,
    "coef": -0.1684778717467914,
    "se": 0.391946867711759,
    "p": 0.6683331011267675,
    "r2": 0.10399031456381946,
    "kind": "Panel TWFE",
    "fe": "Country + Year"
  }
]